voxa_ai/__init__.py
voxa_ai/agent.py
voxa_ai/demo_voxa.py
voxa_ai/offline_qa.json
voxa_ai-2.2.8.data/scripts/voxa-ai.bat
voxa_ai-2.2.8.data/scripts/voxa-ai.sh
voxa_ai-2.2.8.dist-info/METADATA
voxa_ai-2.2.8.dist-info/WHEEL
voxa_ai-2.2.8.dist-info/entry_points.txt
voxa_ai-2.2.8.dist-info/top_level.txt
voxa_ai-2.2.8.dist-info/RECORD
